application_sdk/__init__.py
application_sdk/constants.py
application_sdk/version.py
application_sdk/worker.py
application_sdk/activities/__init__.py
application_sdk/activities/lock_management.py
application_sdk/activities/.cursor/BUGBOT.md
application_sdk/activities/common/__init__.py
application_sdk/activities/common/models.py
application_sdk/activities/common/sql_utils.py
application_sdk/activities/common/utils.py
application_sdk/activities/metadata_extraction/__init__.py
application_sdk/activities/metadata_extraction/base.py
application_sdk/activities/metadata_extraction/rest.py
application_sdk/activities/metadata_extraction/sql.py
application_sdk/activities/query_extraction/__init__.py
application_sdk/activities/query_extraction/sql.py
application_sdk/application/__init__.py
application_sdk/application/metadata_extraction/sql.py
application_sdk/clients/__init__.py
application_sdk/clients/atlan.py
application_sdk/clients/atlan_auth.py
application_sdk/clients/base.py
application_sdk/clients/models.py
application_sdk/clients/redis.py
application_sdk/clients/sql.py
application_sdk/clients/temporal.py
application_sdk/clients/utils.py
application_sdk/clients/workflow.py
application_sdk/clients/.cursor/BUGBOT.md
application_sdk/common/__init__.py
application_sdk/common/aws_utils.py
application_sdk/common/error_codes.py
application_sdk/common/file_converter.py
application_sdk/common/types.py
application_sdk/common/utils.py
application_sdk/common/.cursor/BUGBOT.md
application_sdk/decorators/__init__.py
application_sdk/decorators/locks.py
application_sdk/decorators/mcp_tool.py
application_sdk/decorators/.cursor/BUGBOT.md
application_sdk/docgen/__init__.py
application_sdk/docgen/exporters/__init__.py
application_sdk/docgen/exporters/mkdocs.py
application_sdk/docgen/models/__init__.py
application_sdk/docgen/models/export/__init__.py
application_sdk/docgen/models/export/page.py
application_sdk/docgen/models/manifest/__init__.py
atlan_application_sdk-2.1.1.dist-info/METADATA
atlan_application_sdk-2.1.1.dist-info/WHEEL
atlan_application_sdk-2.1.1.dist-info/licenses/LICENSE
atlan_application_sdk-2.1.1.dist-info/licenses/NOTICE
atlan_application_sdk-2.1.1.dist-info/RECORD
