Metadata-Version: 2.4
Name: atlan-application-sdk
Version: 2.1.1
Summary: Atlan Application SDK is a Python library for developing applications on the Atlan Platform
Project-URL: Repository, https://github.com/atlanhq/application-sdk
Project-URL: Documentation, https://github.com/atlanhq/application-sdk/README.md
Project-URL: Changelog, https://github.com/atlanhq/application-sdk/blob/main/CHANGELOG.md
Author-email: Atlan App Team <connect@atlan.com>
License-Expression: Apache-2.0
License-File: LICENSE
License-File: NOTICE
Keywords: app,atlan,development,platform,sdk
Classifier: Development Status :: 4 - Beta
Classifier: Intended Audience :: Developers
Classifier: License :: OSI Approved :: Apache Software License
Classifier: Operating System :: OS Independent
Classifier: Programming Language :: Python :: 3
Classifier: Programming Language :: Python :: 3.11
Classifier: Programming Language :: Python :: 3.12
Classifier: Programming Language :: Python :: 3.13
Requires-Python: >=3.11
Requires-Dist: aiohttp<3.14.0,>=3.10.0
Requires-Dist: duckdb-engine<0.18.0,>=0.17.0
Requires-Dist: duckdb<1.5.0,>=1.1.3
Requires-Dist: fastapi[standard]==0.127.0
Requires-Dist: loguru<0.8.0,>=0.7.3
Requires-Dist: opentelemetry-exporter-otlp==1.39.1
Requires-Dist: psutil<7.3.0,>=7.0.0
Requires-Dist: pyatlan<8.5.0,>=8.0.2
Requires-Dist: pydantic<2.13.0,>=2.10.6
Requires-Dist: python-dotenv<1.3.0,>=1.1.0
Requires-Dist: uvloop<0.23.0,>=0.21.0; sys_platform != 'win32'
Provides-Extra: daft
Requires-Dist: daft<0.8.0,>=0.7.1; extra == 'daft'
Provides-Extra: distributed-lock
Requires-Dist: redis[hiredis]<7.2.0,>=5.2.0; extra == 'distributed-lock'
Provides-Extra: iam-auth
Requires-Dist: boto3<1.43.0,>=1.38.6; extra == 'iam-auth'
Provides-Extra: mcp
Requires-Dist: fastmcp<2.15.0,>=2.12.3; extra == 'mcp'
Provides-Extra: pandas
Requires-Dist: pandas<2.4.0,>=2.2.3; extra == 'pandas'
Provides-Extra: scale-data-generator
Requires-Dist: faker<39.1.0,>=37.1.0; extra == 'scale-data-generator'
Requires-Dist: numpy<2.5.0,>=1.23.5; extra == 'scale-data-generator'
Requires-Dist: pandas<2.4.0,>=2.2.3; extra == 'scale-data-generator'
Requires-Dist: pyarrow<23.0.0,>=20.0.0; extra == 'scale-data-generator'
Requires-Dist: pyyaml<6.1.0,>=6.0.2; extra == 'scale-data-generator'
Provides-Extra: sqlalchemy
Requires-Dist: sqlalchemy[asyncio]<2.1.0,>=2.0.36; extra == 'sqlalchemy'
Provides-Extra: tests
Requires-Dist: pandas<2.4.0,>=2.2.3; extra == 'tests'
Requires-Dist: pandera[io]<0.28.0,>=0.23.1; extra == 'tests'
Requires-Dist: pytest-order<1.4.0,>=1.3.0; extra == 'tests'
Provides-Extra: workflows
Requires-Dist: dapr==1.16.0; extra == 'workflows'
Requires-Dist: orjson<3.12.0,>=3.10.18; extra == 'workflows'
Requires-Dist: temporalio<1.22.0,>=1.7.1; extra == 'workflows'
